MANIFEST.in
README.txt
setup.py
django_staticblocks.egg-info/PKG-INFO
django_staticblocks.egg-info/SOURCES.txt
django_staticblocks.egg-info/dependency_links.txt
django_staticblocks.egg-info/entry_points.txt
django_staticblocks.egg-info/not-zip-safe
django_staticblocks.egg-info/requires.txt
django_staticblocks.egg-info/top_level.txt
staticblocks/__init__.py
staticblocks/admin.py
staticblocks/forms.py
staticblocks/models.py
staticblocks/templates/staticblock/widgets/block.html
staticblocks/templates/staticblock/widgets/title.html
staticblocks/templatetags/__init__.py
staticblocks/templatetags/static_block.py