Metadata-Version: 1.0
Name: django-staticblocks
Version: 0.4
Summary: staticblocks provides you with tools for content managers to easily include flatpage content as a snippet in your templates while retaining structured control over the templates themselves
Home-page: UNKNOWN
Author: Ethan Jucovy, Rob Marianski
Author-email: ethan.jucovy@gmail.com
License: BSD
Keywords: django template static
Platform: UNKNOWN
Classifier: Framework :: Django
